meshgraph/Graph.py
meshgraph/Node.py
meshgraph/ObjLoader.py
meshgraph/Vec3.py
meshgraph/__init__.py
meshgraph-1.0.0.dist-info/LICENSE
meshgraph-1.0.0.dist-info/METADATA
meshgraph-1.0.0.dist-info/WHEEL
meshgraph-1.0.0.dist-info/top_level.txt
meshgraph-1.0.0.dist-info/RECORD
