Metadata-Version: 2.1
Name: meshgraph
Version: 1.0.0
Summary: 3D mesh to graph
Author-email: Sebastiano Campisi <ianovir@ianovir.com>
License: Apache License
Project-URL: Homepage, https://github.com/ianovir/meshgraph
Project-URL: Bug Tracker, https://github.com/ianovir/meshgraph/issues
Classifier: Programming Language :: Python :: 3
Classifier: License :: OSI Approved :: MIT License
Classifier: Operating System :: OS Independent
Requires-Python: >=3.7
License-File: LICENSE
